mLib-1.2.0.dist-info/DESCRIPTION.rst
mLib-1.2.0.dist-info/METADATA
mLib-1.2.0.dist-info/RECORD
mLib-1.2.0.dist-info/WHEEL
mLib-1.2.0.dist-info/metadata.json
mLib-1.2.0.dist-info/top_level.txt
mlib/__init__.py
mlib/bits.py
mlib/hash.py
mlib/log.py
mlib/memory.py
mlib/misc.py
mlib/parse.py
mlib/rnd.py
mlib/struct.py
mlib/compression/__init__.py
mlib/compression/aplib.py
mlib/compression/lznt1.py
mlib/crypto/__init__.py
mlib/crypto/rc2.py
mlib/crypto/rc6.py
mlib/crypto/spritz.py
mlib/disasm/__init__.py
mlib/disasm/eng.py
mlib/disasm/hash.py
mlib/malware/isfb.py
mlib/malware/pushdo.py
mlib/malware/trickbot.py
mlib/so/_aplib.so
mlib/so/_lzmat.so
mlib/so/_serpent.so
mlib/winapi/__init__.py
mlib/winapi/crypto.py
mlib/winapi/hashdb.py
