Metadata-Version: 2.0
Name: mLib
Version: 1.2.0
Summary: Library contains functions commonly used in malware research
Home-page: https://github.com/mak/mlib
Author: Maciej Kotowicz
Author-email: mak@lokalhost.pl
License: UNKNOWN
Platform: UNKNOWN
Classifier: Development Status :: 5 - Production/Stable
Classifier: License :: Public Domain
Classifier: Operating System :: POSIX :: Linux
Classifier: Programming Language :: Python :: 2 :: Only
Classifier: Programming Language :: Assembly
Classifier: Programming Language :: C
Classifier: Topic :: Utilities
